{
  "run": {
    "date": "2026-06-13",
    "timezone": "America/Sao_Paulo"
  },
  "items": [
    {
      "title": "Notebook Gamer Predator Helios Neo / Phn16-72-74vx / Intel® Core I7-14700hx De 14ªgeração / 16gb / 512ssd / Windows 11 Home / Nvidia Geforce Rtx 4070 Gddr6 / Tela 16",
      "url": "https://www.mercadolivre.com.br/notebook-gamer-predator-helios-neo-phn16-72-74vx-intel-core-i7-14700hx-de-14geraco-16gb-512ssd-windows-11-home-nvidia-geforce-rtx-4070-gddr6-tela-16/p/MLB43497024?pdp_filters=SHIPPING_ORIGIN%3A10215068%7Cprice%3A2000-10000#polycard_client=search-desktop&be_origin=backend&search_layout=grid&position=1&type=product&tracking_id=4695aabb-9cfe-4204-b5f9-5f307fb9a62e&wid=MLB4604579597&sid=search",
      "price_brl": 9698,
      "id": "MLB4604579597",
      "source": "Mercado Livre",
      "term": "14700hx",
      "status": "active",
      "first_seen": "2026-06-13",
      "last_seen": "2026-06-13"
    },
    {
      "title": "Notebook Gamer Acer Predator Helios Neo 16 PHN16-72-75TX • Intel Core i7-14700HX 14ª Geração • 32GB RAM DDR5 • SSD 512GB • RTX 4070 8GB • Windows 11 Home • Tela 16” WQXGA 240Hz",
      "url": "https://www.mercadolivre.com.br/notebook-gamer-acer-predator-helios-neo-16-phn16-72-75tx-intel-core-i7-14700hx-14-geraco-32gb-ram-ddr5-ssd-512gb-rtx-4070-8gb-windows-11-home-tela-16-wqxga-240hz/p/MLB68481578?pdp_filters=SHIPPING_ORIGIN%3A10215068%7Cprice%3A2000-10000#polycard_client=search-desktop&be_origin=backend&search_layout=grid&position=2&type=product&tracking_id=4695aabb-9cfe-4204-b5f9-5f307fb9a62e&wid=MLB4639433915&sid=search",
      "price_brl": 9999,
      "id": "MLB4639433915",
      "source": "Mercado Livre",
      "term": "14700hx",
      "status": "active",
      "first_seen": "2026-06-13",
      "last_seen": "2026-06-13"
    },
    {
      "title": "Notebook Gamer Predator Helios Neo I7-14700hx 16gb Rtx4070",
      "url": "https://www.mercadolivre.com.br/notebook-gamer-predator-helios-neo-i714700hx-16gb-rtx4070/up/MLBU4073346547?pdp_filters=SHIPPING_ORIGIN%3A10215068%7Cprice%3A2000-10000#polycard_client=search-desktop&be_origin=backend&search_layout=grid&position=4&type=product&tracking_id=4695aabb-9cfe-4204-b5f9-5f307fb9a62e&wid=MLB4763407525&sid=search",
      "price_brl": 8799,
      "id": "MLB4763407525",
      "source": "Mercado Livre",
      "term": "14700hx",
      "status": "active",
      "first_seen": "2026-06-13",
      "last_seen": "2026-06-13"
    },
    {
      "title": "Notebook Gamer Predator Helios Neo 16 - Rtx4070 E I7 14700hx",
      "url": "https://produto.mercadolivre.com.br/MLB-6788309860-notebook-gamer-predator-helios-neo-16-rtx4070-e-i7-14700hx-_JM?pdp_filters=SHIPPING_ORIGIN%3A10215068%7Cprice%3A2000-10000#polycard_client=search-desktop&be_origin=backend&search_layout=grid&position=9&type=item&tracking_id=4695aabb-9cfe-4204-b5f9-5f307fb9a62e&wid=MLB6788309860&sid=search",
      "price_brl": 7150,
      "id": "MLB6788309860",
      "source": "Mercado Livre",
      "term": "14700hx",
      "status": "active",
      "first_seen": "2026-06-13",
      "last_seen": "2026-06-13"
    }
  ],
  "price_range_brl": {
    "min": 2000,
    "max": 10000
  }
}